{
    "name": "Heavy Hitter",
    "description": "Your hands do extra damage, but swing slower.",
    "type": "origins:conditioned_attribute",
    "modifiers": [
        {
            "id": "*:*",
            "attribute": "minecraft:generic.attack_damage",
            "amount": 3.515,
            "operation": "add_value"
        },
        {
            "id": "*:*",
            "attribute": "minecraft:generic.attack_speed",
            "amount": -2.2,
            "operation": "add_value"
        }
    ],
    "tick_rate": 1,
    "condition": {
        "type": "origins:equipped_item",
        "equipment_slot": "mainhand",
        "item_condition": {
            "type": "origins:ingredient",
            "ingredient": {
                "tag": "gateway:hell/weapons"
            },
            "inverted": true
        }
    }
}